{
  "accent_strategy": {
    "description": "One faint vermilion beacon with slight atmospheric pulse.",
    "kind": "warning_light",
    "placement": [
      0.76,
      0.25
    ],
    "size": 0.012
  },
  "aspect_mode": "vertical_9x16",
  "beat_id": "benchmark_motion_01",
  "caption_safe_zone": {
    "subtitles": [
      0.08,
      0.74,
      0.92,
      0.96
    ],
    "top_ui": [
      0.0,
      0.0,
      1.0,
      0.12
    ]
  },
  "dominant_mass_strategy": {
    "description": "A weighty ultramarine monolith occupying the right third as the stable architectural mass.",
    "width_ratio": 0.35
  },
  "final_size": {
    "height": 1920,
    "width": 1080
  },
  "historical_anchor": {
    "description": "A launch stack kept nearly static so the frame reads as a restrained witness rather than spectacle.",
    "episode": "Challenger",
    "topic": "Launch motion benchmark"
  },
  "id": "motion_01_shuttle_exterior",
  "motion_preset": "stillness_breathe",
  "outputs": {},
  "prompt_overrides": {
    "scene_intent": "Keep the frame almost locked, letting only atmosphere and reflection carry the motion."
  },
  "reflection_strategy": {
    "description": "A calm mirrored launch-pad plane with restrained surface movement.",
    "horizon_y": 0.63,
    "literal_water": false
  },
  "selected_seed": 2011,
  "source_refs": [],
  "style_profile": "monolith_reflection_v1",
  "subject_anchor": {
    "archetype": "launch_stack",
    "description": "A pale shuttle stack silhouette held nearly static against the field.",
    "placement": [
      0.34,
      0.54
    ],
    "scale": 0.42
  },
  "surreal_breach": {
    "description": "The cold boundary feels too heavy for the sky while the shuttle remains still.",
    "kind": "boundary_pressure"
  },
  "target_duration_seconds": 5.0
}
