{
  "analysis_strategy": "strict_bass_drum_hit_audit_tacoma_737_no_pulse_render",
  "variant_of_hit_map_path": "/Users/mike/Episodes_CascadeEffects/Channel_Trailer/channel_trailer_v2_music_only_bass_drum_only_no_titanic_pulse_breath_background_proof_20260512T152748Z/beat/bass_drum_only_hit_map.json",
  "strict_rule": "only confirmed_bass_drum_hit entries may drive future breath pulses",
  "audit_window_global_seconds": [
    16.6,
    24.0
  ],
  "tacoma_narrows_seconds": [
    16.6,
    20.3
  ],
  "boeing_737_max_seconds": [
    20.3,
    24.0
  ],
  "broad_no_drum_window_inherited": false,
  "broad_no_drum_window_replacement": "explicit_candidate_decisions",
  "candidate_decisions": [
    {
      "index": 1,
      "global_time_seconds": 16.983039,
      "review_reel_time_seconds": 10.983039,
      "audit_window_relative_seconds": 0.383039,
      "subject": "Tacoma Narrows",
      "decision": "rejected_not_bass_drum_hit",
      "decision_source": "current_strict_bass_drum_only_rejected_candidate_map",
      "human_reaudit_required": true,
      "strength": 0.968307,
      "rejection_reason": "not_confirmed_as_audible_bass_drum_hit",
      "nearest_assisted_candidate_global_seconds": 10.983039,
      "sub_bass_35_95_strength": 0.800418183,
      "low_bass_45_130_strength": 0.70958696,
      "bass_body_55_180_strength": 0.224676044
    },
    {
      "index": 2,
      "global_time_seconds": 18.341406,
      "review_reel_time_seconds": 12.341406,
      "audit_window_relative_seconds": 1.741406,
      "subject": "Tacoma Narrows",
      "decision": "rejected_not_bass_drum_hit",
      "decision_source": "current_strict_bass_drum_only_rejected_candidate_map",
      "human_reaudit_required": true,
      "strength": 1.0,
      "rejection_reason": "manual_review_no_audible_bass_drum_prior_low_frequency_false_positive_region",
      "nearest_assisted_candidate_global_seconds": 12.341406,
      "sub_bass_35_95_strength": 1.070067046,
      "low_bass_45_130_strength": 1.154382458,
      "bass_body_55_180_strength": 1.083896452
    },
    {
      "index": 3,
      "global_time_seconds": 18.805805,
      "review_reel_time_seconds": 12.805805,
      "audit_window_relative_seconds": 2.205805,
      "subject": "Tacoma Narrows",
      "decision": "rejected_not_bass_drum_hit",
      "decision_source": "current_strict_bass_drum_only_rejected_candidate_map",
      "human_reaudit_required": true,
      "strength": 0.846605,
      "rejection_reason": "manual_review_no_audible_bass_drum_prior_low_frequency_false_positive_region",
      "nearest_assisted_candidate_global_seconds": 12.805805,
      "sub_bass_35_95_strength": 0.43607985,
      "low_bass_45_130_strength": 0.244270502,
      "bass_body_55_180_strength": 0.257302194
    },
    {
      "index": 4,
      "global_time_seconds": 19.258594,
      "review_reel_time_seconds": 13.258594,
      "audit_window_relative_seconds": 2.658594,
      "subject": "Tacoma Narrows",
      "decision": "rejected_not_bass_drum_hit",
      "decision_source": "current_strict_bass_drum_only_rejected_candidate_map",
      "human_reaudit_required": true,
      "strength": 0.906464,
      "rejection_reason": "manual_review_no_audible_bass_drum_prior_low_frequency_false_positive_region",
      "nearest_assisted_candidate_global_seconds": 13.258594,
      "sub_bass_35_95_strength": 0.766496511,
      "low_bass_45_130_strength": 0.266214038,
      "bass_body_55_180_strength": 0.263129916
    },
    {
      "index": 5,
      "global_time_seconds": 19.711383,
      "review_reel_time_seconds": 13.711383,
      "audit_window_relative_seconds": 3.111383,
      "subject": "Tacoma Narrows",
      "decision": "rejected_not_bass_drum_hit",
      "decision_source": "current_strict_bass_drum_only_rejected_candidate_map",
      "human_reaudit_required": true,
      "strength": 0.834329,
      "rejection_reason": "manual_review_no_audible_bass_drum_prior_low_frequency_false_positive_region",
      "nearest_assisted_candidate_global_seconds": 13.711383,
      "sub_bass_35_95_strength": 0.242805379,
      "low_bass_45_130_strength": 0.324376372,
      "bass_body_55_180_strength": 0.390446457
    },
    {
      "index": 6,
      "global_time_seconds": 20.744671,
      "review_reel_time_seconds": 14.744671,
      "audit_window_relative_seconds": 4.144671,
      "subject": "737 MAX",
      "decision": "rejected_not_bass_drum_hit",
      "decision_source": "current_strict_bass_drum_only_rejected_candidate_map",
      "human_reaudit_required": true,
      "strength": 1.0,
      "rejection_reason": "manual_review_no_audible_bass_drum_prior_low_frequency_false_positive_region",
      "nearest_assisted_candidate_global_seconds": 14.744671,
      "sub_bass_35_95_strength": 0.924528403,
      "low_bass_45_130_strength": 0.95498361,
      "bass_body_55_180_strength": 0.68499147
    },
    {
      "index": 7,
      "global_time_seconds": 21.20907,
      "review_reel_time_seconds": 15.20907,
      "audit_window_relative_seconds": 4.60907,
      "subject": "737 MAX",
      "decision": "confirmed_bass_drum_hit",
      "decision_source": "current_strict_bass_drum_only_hit_map",
      "human_reaudit_required": true,
      "strength": 1.0,
      "rejection_reason": null,
      "nearest_assisted_candidate_global_seconds": 21.20907,
      "sub_bass_35_95_strength": 0.906423017,
      "low_bass_45_130_strength": 0.797416534,
      "bass_body_55_180_strength": 0.372143154
    },
    {
      "index": 8,
      "global_time_seconds": 21.801179,
      "review_reel_time_seconds": 15.801179,
      "audit_window_relative_seconds": 5.201179,
      "subject": "737 MAX",
      "decision": "confirmed_bass_drum_hit",
      "decision_source": "current_strict_bass_drum_only_hit_map",
      "human_reaudit_required": true,
      "strength": 1.0,
      "rejection_reason": null,
      "nearest_assisted_candidate_global_seconds": 21.801179,
      "sub_bass_35_95_strength": 0.863664454,
      "low_bass_45_130_strength": 0.728647875,
      "bass_body_55_180_strength": 0.76409651
    },
    {
      "index": 9,
      "global_time_seconds": 23.147937,
      "review_reel_time_seconds": 17.147937,
      "audit_window_relative_seconds": 6.547937,
      "subject": "737 MAX",
      "decision": "confirmed_bass_drum_hit",
      "decision_source": "current_strict_bass_drum_only_hit_map",
      "human_reaudit_required": true,
      "strength": 1.0,
      "rejection_reason": null,
      "nearest_assisted_candidate_global_seconds": 23.147937,
      "sub_bass_35_95_strength": 1.047499012,
      "low_bass_45_130_strength": 1.059223507,
      "bass_body_55_180_strength": 1.000051189
    },
    {
      "index": 10,
      "global_time_seconds": 23.600726,
      "review_reel_time_seconds": 17.600726,
      "audit_window_relative_seconds": 7.000726,
      "subject": "737 MAX",
      "decision": "confirmed_bass_drum_hit",
      "decision_source": "current_strict_bass_drum_only_hit_map",
      "human_reaudit_required": true,
      "strength": 1.0,
      "rejection_reason": null,
      "nearest_assisted_candidate_global_seconds": 23.600726,
      "sub_bass_35_95_strength": 0.942893703,
      "low_bass_45_130_strength": 0.990888622,
      "bass_body_55_180_strength": 1.028989741
    }
  ],
  "diagnostic_737_timing_peaks": [
    {
      "index": 1,
      "global_time_seconds": 20.793912,
      "review_reel_time_seconds": 14.793912,
      "subject": "737 MAX",
      "source": "full_band_rms_peak_diagnostic_not_candidate_decision",
      "nearest_candidate_global_seconds": 20.744671,
      "nearest_candidate_decision": "rejected_not_bass_drum_hit",
      "nearest_candidate_delta_seconds": 0.049241
    },
    {
      "index": 2,
      "global_time_seconds": 21.242891,
      "review_reel_time_seconds": 15.242891,
      "subject": "737 MAX",
      "source": "full_band_rms_peak_diagnostic_not_candidate_decision",
      "nearest_candidate_global_seconds": 21.20907,
      "nearest_candidate_decision": "confirmed_bass_drum_hit",
      "nearest_candidate_delta_seconds": 0.033821
    },
    {
      "index": 3,
      "global_time_seconds": 22.145839,
      "review_reel_time_seconds": 16.145839,
      "subject": "737 MAX",
      "source": "full_band_rms_peak_diagnostic_not_candidate_decision",
      "nearest_candidate_global_seconds": 21.801179,
      "nearest_candidate_decision": "confirmed_bass_drum_hit",
      "nearest_candidate_delta_seconds": 0.34466
    },
    {
      "index": 4,
      "global_time_seconds": 23.203435,
      "review_reel_time_seconds": 17.203435,
      "subject": "737 MAX",
      "source": "full_band_rms_peak_diagnostic_not_candidate_decision",
      "nearest_candidate_global_seconds": 23.147937,
      "nearest_candidate_decision": "confirmed_bass_drum_hit",
      "nearest_candidate_delta_seconds": 0.055498
    },
    {
      "index": 5,
      "global_time_seconds": 23.652415,
      "review_reel_time_seconds": 17.652415,
      "subject": "737 MAX",
      "source": "full_band_rms_peak_diagnostic_not_candidate_decision",
      "nearest_candidate_global_seconds": 23.600726,
      "nearest_candidate_decision": "confirmed_bass_drum_hit",
      "nearest_candidate_delta_seconds": 0.051689
    }
  ],
  "confirmed_candidate_count": 4,
  "rejected_candidate_count": 6,
  "tacoma_confirmed_candidate_count": 0,
  "boeing_737_max_confirmed_candidate_count": 4,
  "all_candidates_have_binary_decision_read": "pass",
  "human_bass_drum_hit_audit_read": "review_required"
}
