{
  "episode_id": "titanic",
  "status": "blocked_pending_publish_readiness_keep_and_explicit_upload_authorization",
  "privacy_after_explicit_approval": "unlisted",
  "video": {
    "path": "media/titanic_living_cover_final_review_1080p24.mp4",
    "sha256": "82831c630b62f36b83395c59700ce332e3de6b0b31ac8026616f72ce70715f2d",
    "bytes": 158745395
  },
  "captions": {
    "vtt": {
      "path": "captions/titanic_longform.script_locked_rail_safe.offset_intro_3s601.vtt",
      "sha256": "54e673db1fa4834e004c2b441f0b063cf8ad6338f0c01c61dc2e0382f7cf312c",
      "bytes": 18531
    },
    "srt": {
      "path": "captions/titanic_longform.script_locked_rail_safe.offset_intro_3s601.srt",
      "sha256": "f5f6e13618d01af76437e943ae016d0316b892cf05802f6b2bf1990d13152f40",
      "bytes": 19455
    }
  },
  "thumbnail": {
    "path": "thumbnail/titanic_thumbnail_candidate.jpg",
    "sha256": "9b8da395dd902fba28ecdd45faf372df7b74a95aa01b5b6c6c66fe6b0380743b",
    "bytes": 218397
  },
  "metadata": {
    "title": "Titanic and the Lifeboat Regulation Gap",
    "description": "Titanic and the Lifeboat Regulation Gap is a Cascade Effects episode about how small signals become system consequences.\n\nTitanic carried enough lifeboats to satisfy the law, but the law was measuring an older class of risk.\n\nRuntime: about 13 minutes.\n\nCascade Effects traces failures through mechanism, incentives, and institutional blind spots.",
    "chapters": [
      {
        "time": "0:00",
        "seconds": 0,
        "label": "Opening"
      },
      {
        "time": "0:04",
        "seconds": 4,
        "label": "Main episode"
      },
      {
        "time": "11:54",
        "seconds": 713.607007,
        "label": "Closing"
      }
    ],
    "tags": [
      "Cascade Effects",
      "Titanic",
      "documentary",
      "lifeboats",
      "maritime safety",
      "regulation",
      "systems failure"
    ],
    "hashtags": [
      "#CascadeEffects"
    ],
    "category": "Education",
    "language": "en",
    "made_for_kids": false,
    "paid_promotion": false,
    "privacy_after_explicit_approval": "unlisted",
    "public_release_policy": "manual_youtube_studio_only",
    "metadata_path": "metadata/youtube_metadata.json",
    "metadata_sha256": "06e1eb076da7b3c8e18b5f204a2b24974d96516fafb6d133fb31dc02bbc804a7"
  },
  "locks": {
    "publish_ready": false,
    "youtube_upload_ready": false,
    "public_release_ready": false,
    "may_youtube_action": false,
    "upload_allowed": false,
    "upload_performed": false,
    "upload_action_enabled_in_review_html": false,
    "public_release": false,
    "review_upload_privacy_after_approval": "unlisted_after_publish_readiness_keep_and_explicit_upload_approval"
  },
  "may_youtube_action": false,
  "upload_allowed": false,
  "upload_performed": false
}
