{
  "episode_id": "semmelweis",
  "status": "blocked_pending_publish_readiness_keep_and_explicit_upload_authorization",
  "privacy_after_explicit_approval": "unlisted",
  "video": {
    "path": "media/semmelweis_living_cover_final_review_1080p24.mp4",
    "sha256": "8b94722424c9e5f4a24b34f9a6dac0a0a760f41872fb8b8df0210c8a5e900f64",
    "bytes": 328774013
  },
  "captions": {
    "vtt": {
      "path": "captions/semmelweis_longform.script_locked_rail_safe.offset_intro_3s601.vtt",
      "sha256": "decc31ab0c99564e685c68223e7f3180c4a597df8fcea313e75ee5a239dec8e1",
      "bytes": 20874
    },
    "srt": {
      "path": "captions/semmelweis_longform.script_locked_rail_safe.offset_intro_3s601.srt",
      "sha256": "e4fba3ae9bfe221546e77d7f577a09489f643bc80b21c92d1cd441aacf53d3b1",
      "bytes": 21894
    }
  },
  "thumbnail": {
    "path": "thumbnail/semmelweis_thumbnail_candidate.jpg",
    "sha256": "61db7d061550a273a737130755d7aa1fcc6370142cad576e1b61e8617e721bc1",
    "bytes": 170562
  },
  "metadata": {
    "title": "Semmelweis",
    "description": "Semmelweis is a Cascade Effects episode about how small signals become system consequences.\n\nA simple handwashing observation collided with medical authority, hierarchy, and disbelief.\n\nRuntime: about 15 minutes.\n\nCascade Effects traces failures through mechanism, incentives, and institutional blind spots.",
    "chapters": [
      {
        "time": "0:00",
        "seconds": 0.0,
        "label": "Measured, Not Explained"
      },
      {
        "time": "1:18",
        "seconds": 77.856,
        "label": "Two Wards, Same Roof"
      },
      {
        "time": "2:55",
        "seconds": 175.201,
        "label": "Autopsy To Ward"
      },
      {
        "time": "4:36",
        "seconds": 275.702,
        "label": "The Evidence Had Layers"
      },
      {
        "time": "6:41",
        "seconds": 400.994,
        "label": "The Result Became An Accusation"
      },
      {
        "time": "8:37",
        "seconds": 516.678,
        "label": "Resistance Hardened"
      },
      {
        "time": "10:19",
        "seconds": 619.001,
        "label": "Wrong In A Structural Way"
      },
      {
        "time": "12:25",
        "seconds": 744.522,
        "label": "The Data Was Always Sufficient"
      }
    ],
    "tags": [
      "Cascade Effects",
      "Semmelweis",
      "documentary",
      "handwashing",
      "medical history",
      "public health",
      "systems failure"
    ],
    "hashtags": [
      "#CascadeEffects"
    ],
    "category": "Education",
    "language": "en",
    "made_for_kids": false,
    "paid_promotion": false,
    "privacy_after_explicit_approval": "unlisted",
    "public_release_policy": "manual_youtube_studio_only",
    "metadata_path": "metadata/youtube_metadata.json",
    "metadata_sha256": "84dd2b0fcf4eccda5ef4a90a65ee682b33dc5b3c6d35a1cc94573d3af6bd0691"
  },
  "locks": {
    "publish_ready": false,
    "youtube_upload_ready": false,
    "public_release_ready": false,
    "may_youtube_action": false,
    "upload_allowed": false,
    "upload_performed": false,
    "upload_action_enabled_in_review_html": false,
    "public_release": false,
    "review_upload_privacy_after_approval": "unlisted_after_publish_readiness_keep_and_explicit_upload_approval"
  },
  "may_youtube_action": false,
  "upload_allowed": false,
  "upload_performed": false
}
